{
  "schema": "rm152-native-matrix-v1",
  "environment_discovery": {
    "os": "Windows 10.0.19045",
    "display_count": 1,
    "display": "1920x1080; available 1920x1040; logical DPI 96; DPR 1.0",
    "narrator_binary_present": true,
    "high_contrast_active": false,
    "windows_automation_connection": "connected after Codex Desktop restart",
    "launch_identity_correction": "The initial same-name launch resolved to the installed Program Files executable and was discarded; an identical uniquely named artifact was then confirmed as the exact dist process.",
    "windows_state_capture": "Exact-build screenshot capture failed with SetIsBorderRequired/interface not supported (0x80004002); exact-build text-only UI Automation succeeded in an earlier run.",
    "text_only_ui_automation": "Exact build exposed a 176-element tree with names, roles, states, and table values.",
    "keyboard_probe": "The focused-element report remained on global search while keyboard behaviour changed the active route to Analytics; input calls also timed out intermittently, so no focus or keyboard verdict was accepted.",
    "owner_keyboard_observation": {
      "observed_at": "2026-07-20 Europe/Moscow",
      "artifact_sha256": "4D69D6B2378E77DBD179B86A8513FFB0CA20685489659F21778C3CD868F454D6",
      "environment": "single 1920x1080 display; logical DPI 96; exact frozen build",
      "confirmed": [
        "Visible focus was observed and moved between controls.",
        "The requested Tab sweep did not become trapped.",
        "Shift+Tab moved focus backward.",
        "No clipped or overlapping text was observed in the displayed state."
      ],
      "theme_result": "Keyboard traversal continued to work after switching from light to dark, but dark theme exposed white fallback strips on native table, scrollbar, tab, progress, and controller-owned search surfaces.",
      "unresolved": [
        "complete forward and reverse order",
        "all semantic states",
        "Narrator output"
      ],
      "status_policy": "Partial owner observation only; no cell promoted."
    },
    "frozen_executable_sha256": "81A11CF64665E61A29739F349BA435F21B234252476B46917DC8D8A0D342A866",
    "frozen_self_test": "PASS; 9 isolated automated checks",
    "dark_theme_fix_rerun": {
      "defect_artifact_sha256": "4D69D6B2378E77DBD179B86A8513FFB0CA20685489659F21778C3CD868F454D6",
      "fix_commit": "9da4f79",
      "candidate_artifact_sha256": "81A11CF64665E61A29739F349BA435F21B234252476B46917DC8D8A0D342A866",
      "candidate_frozen_self_test": "PASS; 9 isolated automated checks",
      "native_visual_status": "PENDING"
    },
    "frozen_manifest_dpi_declaration": "absent",
    "observation_boundary": "Exact artifact identity, a text-only UIA tree, and owner-observed visible moving focus were recorded, but complete keyboard, screenshot, Narrator, DPI, and reliable focus-order evidence were not; no native cell promoted."
  },
  "cells": [
    {
      "id": "SR-01-DEV",
      "status": "NOT_EXECUTED",
      "observed": false,
      "environment": {},
      "evidence": [],
      "note": "Native observation required; automated evidence is not a substitute."
    },
    {
      "id": "SR-01-FROZEN",
      "status": "NOT_EXECUTED",
      "observed": false,
      "environment": {},
      "evidence": [],
      "note": "Native observation required; automated evidence is not a substitute."
    },
    {
      "id": "SR-02-DEV",
      "status": "NOT_EXECUTED",
      "observed": false,
      "environment": {},
      "evidence": [],
      "note": "Native observation required; automated evidence is not a substitute."
    },
    {
      "id": "SR-02-FROZEN",
      "status": "NOT_EXECUTED",
      "observed": false,
      "environment": {},
      "evidence": [],
      "note": "Native observation required; automated evidence is not a substitute."
    },
    {
      "id": "SR-03-DEV",
      "status": "NOT_EXECUTED",
      "observed": false,
      "environment": {},
      "evidence": [],
      "note": "Native observation required; automated evidence is not a substitute."
    },
    {
      "id": "SR-03-FROZEN",
      "status": "NOT_EXECUTED",
      "observed": false,
      "environment": {},
      "evidence": [],
      "note": "Native observation required; automated evidence is not a substitute."
    },
    {
      "id": "SR-04-DEV",
      "status": "NOT_EXECUTED",
      "observed": false,
      "environment": {},
      "evidence": [],
      "note": "Native observation required; automated evidence is not a substitute."
    },
    {
      "id": "SR-04-FROZEN",
      "status": "NOT_EXECUTED",
      "observed": false,
      "environment": {},
      "evidence": [],
      "note": "Native observation required; automated evidence is not a substitute."
    },
    {
      "id": "SR-05-DEV",
      "status": "NOT_EXECUTED",
      "observed": false,
      "environment": {},
      "evidence": [],
      "note": "Native observation required; automated evidence is not a substitute."
    },
    {
      "id": "SR-05-FROZEN",
      "status": "NOT_EXECUTED",
      "observed": false,
      "environment": {},
      "evidence": [],
      "note": "Native observation required; automated evidence is not a substitute."
    },
    {
      "id": "SR-06-DEV",
      "status": "NOT_EXECUTED",
      "observed": false,
      "environment": {},
      "evidence": [],
      "note": "Native observation required; automated evidence is not a substitute."
    },
    {
      "id": "SR-06-FROZEN",
      "status": "NOT_EXECUTED",
      "observed": false,
      "environment": {},
      "evidence": [],
      "note": "Native observation required; automated evidence is not a substitute."
    },
    {
      "id": "SR-07-DEV",
      "status": "NOT_EXECUTED",
      "observed": false,
      "environment": {},
      "evidence": [],
      "note": "Native observation required; automated evidence is not a substitute."
    },
    {
      "id": "SR-07-FROZEN",
      "status": "NOT_EXECUTED",
      "observed": false,
      "environment": {},
      "evidence": [],
      "note": "Native observation required; automated evidence is not a substitute."
    },
    {
      "id": "SR-08-DEV",
      "status": "NOT_EXECUTED",
      "observed": false,
      "environment": {},
      "evidence": [],
      "note": "Native observation required; automated evidence is not a substitute."
    },
    {
      "id": "SR-08-FROZEN",
      "status": "NOT_EXECUTED",
      "observed": false,
      "environment": {},
      "evidence": [],
      "note": "Native observation required; automated evidence is not a substitute."
    },
    {
      "id": "SR-09-DEV",
      "status": "NOT_EXECUTED",
      "observed": false,
      "environment": {},
      "evidence": [],
      "note": "Native observation required; automated evidence is not a substitute."
    },
    {
      "id": "SR-09-FROZEN",
      "status": "NOT_EXECUTED",
      "observed": false,
      "environment": {},
      "evidence": [],
      "note": "Native observation required; automated evidence is not a substitute."
    },
    {
      "id": "SR-10-DEV",
      "status": "NOT_EXECUTED",
      "observed": false,
      "environment": {},
      "evidence": [],
      "note": "Native observation required; automated evidence is not a substitute."
    },
    {
      "id": "SR-10-FROZEN",
      "status": "NOT_EXECUTED",
      "observed": false,
      "environment": {},
      "evidence": [],
      "note": "Native observation required; automated evidence is not a substitute."
    },
    {
      "id": "SR-11-DEV",
      "status": "NOT_EXECUTED",
      "observed": false,
      "environment": {},
      "evidence": [],
      "note": "Native observation required; automated evidence is not a substitute."
    },
    {
      "id": "SR-11-FROZEN",
      "status": "NOT_EXECUTED",
      "observed": false,
      "environment": {},
      "evidence": [],
      "note": "Native observation required; automated evidence is not a substitute."
    },
    {
      "id": "NATIVE-1366-100-DL",
      "status": "NOT_EXECUTED",
      "observed": false,
      "environment": {},
      "evidence": [],
      "note": "Native observation required; automated evidence is not a substitute."
    },
    {
      "id": "NATIVE-1366-125-DL",
      "status": "NOT_EXECUTED",
      "observed": false,
      "environment": {},
      "evidence": [],
      "note": "Native observation required; automated evidence is not a substitute."
    },
    {
      "id": "NATIVE-1920-100-DL",
      "status": "FAIL",
      "observed": true,
      "environment": {
        "os": "Windows 10.0.19045",
        "display": "1920x1080; available 1920x1040",
        "scale": "100%; logical DPI 96; DPR 1.0",
        "theme": "light and dark; dark theme visual defect observed",
        "artifact_sha256": "4D69D6B2378E77DBD179B86A8513FFB0CA20685489659F21778C3CD868F454D6",
        "observer": "project owner",
        "observed_at": "2026-07-20 Europe/Moscow"
      },
      "evidence": [
        "Visible focus was observed moving between controls.",
        "Tab did not become trapped in the requested sweep.",
        "Shift+Tab moved focus backward.",
        "No clipped or overlapping text was observed in the displayed state.",
        "Dark theme showed white fallback strips on native table, scrollbar, tab, progress, and controller-owned search surfaces."
      ],
      "note": "FAIL is retained for the original observed artifact. Fixed artifact 81A11CF64665E61A29739F349BA435F21B234252476B46917DC8D8A0D342A866 passed its frozen self-test and awaits a native visual rerun; all semantic states, complete route order, and Narrator output also remain incomplete."
    },
    {
      "id": "NATIVE-1920-125-DL",
      "status": "NOT_EXECUTED",
      "observed": false,
      "environment": {},
      "evidence": [],
      "note": "Native observation required; automated evidence is not a substitute."
    },
    {
      "id": "NATIVE-1920-150-DL",
      "status": "NOT_EXECUTED",
      "observed": false,
      "environment": {},
      "evidence": [],
      "note": "Native observation required; automated evidence is not a substitute."
    },
    {
      "id": "NATIVE-2560-150-DL",
      "status": "NOT_EXECUTED",
      "observed": false,
      "environment": {},
      "evidence": [],
      "note": "Native observation required; automated evidence is not a substitute."
    },
    {
      "id": "NATIVE-2560-175-DL",
      "status": "NOT_EXECUTED",
      "observed": false,
      "environment": {},
      "evidence": [],
      "note": "Native observation required; automated evidence is not a substitute."
    },
    {
      "id": "NATIVE-3840-200-DL",
      "status": "NOT_EXECUTED",
      "observed": false,
      "environment": {},
      "evidence": [],
      "note": "Native observation required; automated evidence is not a substitute."
    },
    {
      "id": "NATIVE-HC",
      "status": "NOT_EXECUTED",
      "observed": false,
      "environment": {},
      "evidence": [],
      "note": "Native observation required; automated evidence is not a substitute."
    },
    {
      "id": "NATIVE-MIXED-DPI",
      "status": "NOT_EXECUTED",
      "observed": false,
      "environment": {},
      "evidence": [],
      "note": "Native observation required; automated evidence is not a substitute."
    },
    {
      "id": "NATIVE-FROZEN",
      "status": "NOT_EXECUTED",
      "observed": false,
      "environment": {},
      "evidence": [],
      "note": "Native observation required; automated evidence is not a substitute."
    }
  ]
}
